sqlalchemy_pydantic_codegen/__init__.py
sqlalchemy_pydantic_codegen/cli.py
sqlalchemy_pydantic_codegen/core/__init__.py
sqlalchemy_pydantic_codegen/core/cleaner.py
sqlalchemy_pydantic_codegen/core/generator.py
sqlalchemy_pydantic_codegen/core/templates.py
sqlalchemy_pydantic_codegen/templates/__init__.py
sqlalchemy_pydantic_codegen/templates/init.jinja2
sqlalchemy_pydantic_codegen/templates/model.jinja2
sqlalchemy_pydantic_codegen/templates/schema.jinja2
sqlalchemy_pydantic_codegen/utils/__init__.py
sqlalchemy_pydantic_codegen/utils/extract_model.py
sqlalchemy_pydantic_codegen/utils/type_mapping.py
sqlalchemy_pydantic_codegen-1.0.1.dist-info/licenses/LICENSE
sqlalchemy_pydantic_codegen-1.0.1.dist-info/METADATA
sqlalchemy_pydantic_codegen-1.0.1.dist-info/WHEEL
sqlalchemy_pydantic_codegen-1.0.1.dist-info/entry_points.txt
sqlalchemy_pydantic_codegen-1.0.1.dist-info/top_level.txt
sqlalchemy_pydantic_codegen-1.0.1.dist-info/RECORD
