Metadata-Version: 2.4
Name: sqlalchemy-pydantic-codegen
Version: 1.0.1
Summary: A library to generate Pydantic models from SQLAlchemy models.
Home-page: https://github.com/dsanmart/sqlalchemy-pydantic-codegen
Author: Dsanmart
License: MIT
Project-URL: Homepage, https://github.com/dsanmart/sqlalchemy-pydantic-codegen
Project-URL: Repository, https://github.com/dsanmart/sqlalchemy-pydantic-codegen
Project-URL: Issues, https://github.com/dsanmart/sqlalchemy-pydantic-codegen/issues
Keywords: sqlalchemy,pydantic,codegen,models
Requires-Python: >=3.6
License-File: LICENSE
Requires-Dist: sqlalchemy>=1.4
Requires-Dist: pydantic>=1.8
Requires-Dist: jinja2>=3.0
Requires-Dist: python-dotenv>=1.0.1
Requires-Dist: ruff>=0.13.1
Dynamic: author
Dynamic: home-page
Dynamic: license-file
Dynamic: requires-python
